kostal/__init__.py
kostal/plenticore/__init__.py
kostal/plenticore/cli.py
kostal_plenticore-0.2.0.dist-info/LICENSE
kostal_plenticore-0.2.0.dist-info/METADATA
kostal_plenticore-0.2.0.dist-info/WHEEL
kostal_plenticore-0.2.0.dist-info/entry_points.txt
kostal_plenticore-0.2.0.dist-info/top_level.txt
kostal_plenticore-0.2.0.dist-info/RECORD
