Metadata-Version: 2.1
Name: kostal-plenticore
Version: 0.2.0
Summary: Kostal Plenticore REST-API client
Home-page: https://github.com/stegm/kostal_plenticore
Author: @stegm
License: UNKNOWN
Platform: UNKNOWN
Classifier: Development Status :: 4 - Beta
Classifier: Environment :: Console
Classifier: Intended Audience :: Developers
Classifier: License :: OSI Approved :: Apache Software License
Classifier: Programming Language :: Python :: 3.8
Classifier: Topic :: Software Development :: Libraries
Requires-Dist: aiohttp (>=3.6)
Requires-Dist: pycryptodome (>=3.9)
Provides-Extra: cli
Requires-Dist: prompt-toolkit (>=3.0) ; extra == 'cli'
Requires-Dist: click (>=7.1) ; extra == 'cli'
